COPYING
MANIFEST.in
pyproject.toml
setup.py
NferModule.egg-info/PKG-INFO
NferModule.egg-info/SOURCES.txt
NferModule.egg-info/dependency_links.txt
NferModule.egg-info/not-zip-safe
NferModule.egg-info/requires.txt
NferModule.egg-info/top_level.txt
gensrc/parser/dsl.tab.c
gensrc/parser/dsl.tab.h
gensrc/parser/dsl.yy.c
inc/analysis.h
inc/ast.h
inc/astutil.h
inc/compile.h
inc/debug.h
inc/dict.h
inc/dsl.h
inc/expression.h
inc/file.h
inc/generate.h
inc/learn.h
inc/log.h
inc/map.h
inc/memory.h
inc/nfer.h
inc/pool.h
inc/rdc.h
inc/semantic.h
inc/stack.h
inc/static.h
inc/strings.h
inc/target.h
inc/types.h
python/README.md
python/nfer/__init__.py
python/nfer/gui.py
python/nfer/instrument.py
python/nfer/nfer.py
python/nfer/normalize.py
python/nfer/rules.py
python/nfer/static/d3.min.js
python/nfer/static/favicon.ico
python/nfer/static/nfergui.js
python/nfer/static/socket.io.min.js
python/nfer/static/socket.io.min.js.map
python/nfer/www/index.html
python/src/pyinterface.c
src/analysis.c
src/dict.c
src/expression.c
src/file.c
src/learn.c
src/log.c
src/map.c
src/memory.c
src/nfer.c
src/pool.c
src/stack.c
src/strings.c
src/types.c
src/dsl/ast.c
src/dsl/astutil.c
src/dsl/generate.c
src/dsl/static.c
src/dsl/semantics/constants.c
src/dsl/semantics/fields.c
src/dsl/semantics/imports.c
src/dsl/semantics/labels.c
src/dsl/semantics/literals.c
src/dsl/semantics/typecheck.c