Metadata-Version: 2.1
Name: NferModule
Version: 0.16.0
Summary: The nfer language for Python
Home-page: http://nfer.io/
Author: Sean Kauffman
Author-email: seank@cs.aau.dk
Requires-Python: >=3.5
License-File: COPYING
